zappa_call_later/.DS_Store
zappa_call_later/__init__.py
zappa_call_later/admin.py
zappa_call_later/models.py
zappa_call_later/views.py
zappa_call_later/zappa_check.py
zappa_call_later/management/__init__.py
zappa_call_later/management/commands/__init__.py
zappa_call_later/management/commands/check_for_tasks.py
zappa_call_later/migrations/0001_initial.py
zappa_call_later/migrations/__init__.py
django_zappa_call_later-0.1.dist-info/LICENSE
django_zappa_call_later-0.1.dist-info/METADATA
django_zappa_call_later-0.1.dist-info/WHEEL
django_zappa_call_later-0.1.dist-info/top_level.txt
django_zappa_call_later-0.1.dist-info/RECORD
