Metadata-Version: 2.1
Name: django-zappa-call-later
Version: 0.1
Summary: A simple Django app to queue task using zappa.
Home-page: https://github.com/Bulletninja/zappa-call-later
Author: Luis Valenzuela
Author-email: luis@suscribe.la
License: MIT License
Platform: UNKNOWN
Classifier: Environment :: Web Environment
Classifier: Framework :: Django
Classifier: Framework :: Django :: 1.11
Classifier: Intended Audience :: Developers
Classifier: License :: OSI Approved :: MIT License
Classifier: Operating System :: OS Independent
Classifier: Programming Language :: Python
Classifier: Programming Language :: Python :: 3.5
Classifier: Programming Language :: Python :: 3.6
Classifier: Topic :: Internet :: WWW/HTTP
